{
  "name": "Marketing Portal Professional Dev",
  "dockerComposeFile": "../docker-compose.yml",
  "service": "app",
  "workspaceFolder": "/app",
  "features": {
    "ghcr.io/devcontainers/features/node:1": {
      "version": "20",
      "nodeGypDependencies": true,
      "installYarnUsingApt": true
    },
    "ghcr.io/devcontainers/features/python:1": {
      "version": "3.11",
      "installTools": true,
      "optimize": true
    },
    "ghcr.io/devcontainers/features/docker-outside-of-docker:1": {
      "version": "latest",
      "enableNonRootDocker": "true",
      "moby": "true"
    },
    "ghcr.io/devcontainers/features/common-utils:2": {
      "configureZshAsDefaultShell": true,
      "username": "node"
    },
    "ghcr.io/devcontainers/features/git:1": {}
  },
  "containerEnv": {
    "LANG": "C.UTF-8",
    "LC_ALL": "C.UTF-8",
    "POETRY_VIRTUALENVS_IN_PROJECT": "true"
  },
  "customizations": {
    "vscode": {
      "extensions": [
        "ms-vscode.vscode-typescript-next",
        "esbenp.prettier-vscode",
        "dbaeumer.vscode-eslint",
        "ms-vscode.vscode-json",
        "ms-playwright.playwright",
        "kilocode.kilo-code",
        "ms-azuretools.vscode-docker",
        "ms-python.python",
        "ms-python.vscode-pylance",
        "eamodio.gitlens",
        "donjayamanne.githistory",
        "vivaxy.vscode-conventional-commits",
        "mhutchie.git-graph",
        "humao.rest-client",
        "yzhang.markdown-all-in-one",
        "davidanson.vscode-markdownlint",
        "tamasfe.even-better-toml",
        "redhat.vscode-yaml"
      ],
      "settings": {
        "editor.formatOnSave": true,
        "editor.defaultFormatter": "esbenp.prettier-vscode",
        "eslint.enable": true,
        "typescript.preferences.importModuleSpecifier": "relative",
        "playwright.reuseBrowser": true,
        "kilocode.model": "x-ai/grok-code-fast-1",
        "terminal.integrated.defaultProfile.linux": "zsh",
        "python.defaultInterpreterPath": "/app/.venv/bin/python",
        "python.formatting.provider": "black"
      }
    }
  },
  "remoteUser": "node",
  "postStartCommand": "bash .devcontainer/setup.sh"
}
